odoo/addons/account_payment_multi_deduction/README.rst
odoo/addons/account_payment_multi_deduction/__init__.py
odoo/addons/account_payment_multi_deduction/__manifest__.py
odoo/addons/account_payment_multi_deduction/i18n/account_payment_multi_deduction.pot
odoo/addons/account_payment_multi_deduction/i18n/it.po
odoo/addons/account_payment_multi_deduction/models/__init__.py
odoo/addons/account_payment_multi_deduction/models/account_payment.py
odoo/addons/account_payment_multi_deduction/readme/CONTRIBUTORS.md
odoo/addons/account_payment_multi_deduction/readme/DESCRIPTION.md
odoo/addons/account_payment_multi_deduction/readme/HISTORY.md
odoo/addons/account_payment_multi_deduction/readme/USAGE.md
odoo/addons/account_payment_multi_deduction/security/ir.model.access.csv
odoo/addons/account_payment_multi_deduction/static/description/icon.png
odoo/addons/account_payment_multi_deduction/static/description/index.html
odoo/addons/account_payment_multi_deduction/tests/__init__.py
odoo/addons/account_payment_multi_deduction/tests/test_payment_multi_deduction.py
odoo/addons/account_payment_multi_deduction/wizard/__init__.py
odoo/addons/account_payment_multi_deduction/wizard/account_payment_deduction.py
odoo/addons/account_payment_multi_deduction/wizard/account_payment_register.py
odoo/addons/account_payment_multi_deduction/wizard/account_payment_register_views.xml
odoo_addon_account_payment_multi_deduction-17.0.1.0.0.2.dist-info/METADATA
odoo_addon_account_payment_multi_deduction-17.0.1.0.0.2.dist-info/WHEEL
odoo_addon_account_payment_multi_deduction-17.0.1.0.0.2.dist-info/top_level.txt
odoo_addon_account_payment_multi_deduction-17.0.1.0.0.2.dist-info/RECORD
